<annotation>
	<folder>train</folder>
	<filename>crop001140.jpg</filename>
	<path>/home/jideon/Documents/person data/images/train/crop001140.jpg</path>
	<source>
		<database>Unknown</database>
	</source>
	<size>
		<width>504</width>
		<height>708</height>
		<depth>3</depth>
	</size>
	<segmented>0</segmented>
	<object>
		<name>person</name>
		<pose>Unspecified</pose>
		<truncated>0</truncated>
		<difficult>0</difficult>
		<bndbox>
			<xmin>180</xmin>
			<ymin>213</ymin>
			<xmax>302</xmax>
			<ymax>634</ymax>
		</bndbox>
	</object>
	<object>
		<name>person</name>
		<pose>Unspecified</pose>
		<truncated>0</truncated>
		<difficult>0</difficult>
		<bndbox>
			<xmin>58</xmin>
			<ymin>111</ymin>
			<xmax>197</xmax>
			<ymax>340</ymax>
		</bndbox>
	</object>
	<object>
		<name>person</name>
		<pose>Unspecified</pose>
		<truncated>1</truncated>
		<difficult>0</difficult>
		<bndbox>
			<xmin>422</xmin>
			<ymin>180</ymin>
			<xmax>504</xmax>
			<ymax>708</ymax>
		</bndbox>
	</object>
</annotation>
