<annotation>
	<folder>train</folder>
	<filename>crop001016.jpg</filename>
	<path>/home/jideon/Documents/person data/images/train/crop001016.jpg</path>
	<source>
		<database>Unknown</database>
	</source>
	<size>
		<width>724</width>
		<height>976</height>
		<depth>3</depth>
	</size>
	<segmented>0</segmented>
	<object>
		<name>person</name>
		<pose>Unspecified</pose>
		<truncated>0</truncated>
		<difficult>0</difficult>
		<bndbox>
			<xmin>267</xmin>
			<ymin>335</ymin>
			<xmax>440</xmax>
			<ymax>699</ymax>
		</bndbox>
	</object>
	<object>
		<name>person</name>
		<pose>Unspecified</pose>
		<truncated>0</truncated>
		<difficult>0</difficult>
		<bndbox>
			<xmin>270</xmin>
			<ymin>238</ymin>
			<xmax>420</xmax>
			<ymax>411</ymax>
		</bndbox>
	</object>
</annotation>
